nbck_input/__init__.py
nbck_input/base.py
nbck_input/keys.py
nbck_input/linux.py
nbck_input/prompts.py
nbck_input/utils.py
nbck_input/win32.py
NonBlockInput-1.0.1.dist-info/LICENSE
NonBlockInput-1.0.1.dist-info/METADATA
NonBlockInput-1.0.1.dist-info/WHEEL
NonBlockInput-1.0.1.dist-info/top_level.txt
NonBlockInput-1.0.1.dist-info/RECORD
