Metadata-Version: 2.1
Name: NonBlockInput
Version: 1.0.1
Summary: This is a non-blocking input library
Home-page: UNKNOWN
Author: hao.zeng
Author-email: zh66920164@outlook.com
License: MIT
Platform: UNKNOWN
Classifier: Programming Language :: Python :: 3
License-File: LICENSE
Requires-Dist: pyte
